nucleus/__init__.py
nucleus/logger.py
nucleus/main.py
nucleus/models.py
nucleus/prompts.py
nucleus/test.ipynb
nucleus/tools.py
nucleus/data_viz/__init__.py
nucleus/data_viz/app.py
nucleus/data_viz/dependencies.py
nucleus/data_viz/planner.py
nucleus/data_viz/server.py
nucleus/terminal/__init__.py
nucleus/terminal/planner.py
nucleus/terminal/suggestion.py
nucleus/visualization/.gitignore
nucleus/visualization/README.md
nucleus/visualization/eslint.config.js
nucleus/visualization/index.html
nucleus/visualization/package.json
nucleus/visualization/vite.config.js
nucleus/visualization/yarn.lock
nucleus/visualization/dist/index.html
nucleus/visualization/dist/vite.svg
nucleus/visualization/dist/assets/AbortablePromiseCache-xs5eyOH3.js
nucleus/visualization/dist/assets/AboutDialog-BRPF6WXY.js
nucleus/visualization/dist/assets/AddConnectionWidget-DUN-IkoP.js
nucleus/visualization/dist/assets/AddConnectionWidget-mis7YdO-.js
nucleus/visualization/dist/assets/AddCustomPluginDialog-BNLTB2A8.js
nucleus/visualization/dist/assets/AddCustomPluginDialog-Dt00BL8_.js
nucleus/visualization/dist/assets/AddFiltersDialog-CHG1ENFG.js
nucleus/visualization/dist/assets/AddFiltersDialog-CoqzwTsE.js
nucleus/visualization/dist/assets/AddTrackWidget-BMjJvS50.js
nucleus/visualization/dist/assets/AddTrackWidget-CyPxzhjC.js
nucleus/visualization/dist/assets/AddTrackWorkflow-B8I-JaR_.js
nucleus/visualization/dist/assets/AddTrackWorkflow-D98T5Tmr.js
nucleus/visualization/dist/assets/AlignmentsFeatureDetail-Ah8jH9Px.js
nucleus/visualization/dist/assets/AlignmentsFeatureDetail-sMQ4gXe4.js
nucleus/visualization/dist/assets/ArcTooltip-C_3QYB2A.js
nucleus/visualization/dist/assets/ArcTooltip-Cw0AnUyl.js
nucleus/visualization/dist/assets/Arcs-BDg83GWX.js
nucleus/visualization/dist/assets/Arcs-BHxqO6AV.js
nucleus/visualization/dist/assets/BamAdapter-BR_9DsQb.js
nucleus/visualization/dist/assets/BamAdapter-ClyYMAHa.js
nucleus/visualization/dist/assets/BaseCard-BEWjgl8a.js
nucleus_chat-0.4.0.dist-info/METADATA
nucleus_chat-0.4.0.dist-info/WHEEL
nucleus_chat-0.4.0.dist-info/entry_points.txt
nucleus_chat-0.4.0.dist-info/top_level.txt
nucleus_chat-0.4.0.dist-info/RECORD
